sortinghat/_version.py
sortinghat/app/__init__.py
sortinghat/app/schema.py
sortinghat/app/urls.py
sortinghat/app/wsgi.py
sortinghat/cli/__init__.py
sortinghat/cli/client/__init__.py
sortinghat/cli/client/client.py
sortinghat/cli/client/schema.py
sortinghat/cli/cmds/__init__.py
sortinghat/cli/cmds/add.py
sortinghat/cli/cmds/config.py
sortinghat/cli/cmds/countries.py
sortinghat/cli/cmds/enroll.py
sortinghat/cli/cmds/lock.py
sortinghat/cli/cmds/merge.py
sortinghat/cli/cmds/mv.py
sortinghat/cli/cmds/orgs.py
sortinghat/cli/cmds/profile.py
sortinghat/cli/cmds/rm.py
sortinghat/cli/cmds/show.py
sortinghat/cli/cmds/split.py
sortinghat/cli/cmds/withdraw.py
sortinghat/cli/sortinghat.py
sortinghat/cli/templates/add.tmpl
sortinghat/cli/templates/config.tmpl
sortinghat/cli/templates/countries.tmpl
sortinghat/cli/templates/lock.tmpl
sortinghat/cli/templates/mv.tmpl
sortinghat/cli/templates/organizations.tmpl
sortinghat/cli/templates/profile.tmpl
sortinghat/cli/templates/rm.tmpl
sortinghat/cli/templates/show.tmpl
sortinghat/cli/templates/split.tmpl
sortinghat/cli/utils.py
sortinghat/config/__init__.py
sortinghat/config/permission_groups.json
sortinghat/config/settings.py
sortinghat/config/tenants.json
sortinghat/core/admin.py
sortinghat/core/api.py
sortinghat/core/apps.py
sortinghat/core/aux.py
sortinghat/core/context.py
sortinghat/core/db.py
sortinghat/core/decorators.py
sortinghat/core/errors.py
sortinghat/core/fixtures/countries.json
sortinghat/core/importer/backend.py
sortinghat/core/importer/backends/gitdm.py
sortinghat/core/importer/backends/mailmap.py
sortinghat/core/importer/base.py
sortinghat/core/importer/models.py
sortinghat/core/importer/utils.py
sortinghat/core/jobs.py
sortinghat/core/log.py
sortinghat/core/management/__init__.py
sortinghat/core/management/commands/__init__.py
sortinghat/core/management/commands/create_groups.py
sortinghat/core/management/commands/set_permissions.py
sortinghat/core/middleware.py
sortinghat/core/migrations/0001_sortinghat.py
sortinghat-1.13.0.dist-info/METADATA
sortinghat-1.13.0.dist-info/WHEEL
sortinghat-1.13.0.dist-info/entry_points.txt
sortinghat-1.13.0.dist-info/licenses/AUTHORS
sortinghat-1.13.0.dist-info/licenses/LICENSE
sortinghat-1.13.0.dist-info/RECORD
