Metadata-Version: 2.4
Name: sortinghat
Version: 1.13.0
Summary: A tool to manage identities.
License: GPL-3.0+
License-File: AUTHORS
License-File: LICENSE
Keywords: development,grimoirelab
Author: GrimoireLab Developers
Requires-Python: >=3.10,<4.0
Classifier: Development Status :: 5 - Production/Stable
Classifier: Intended Audience :: Developers
Classifier: License :: OSI Approved :: GNU General Public License v3 or later (GPLv3+)
Classifier: Programming Language :: Python :: 3
Classifier: Programming Language :: Python :: 3.10
Classifier: Programming Language :: Python :: 3.11
Classifier: Programming Language :: Python :: 3.12
Classifier: Programming Language :: Python :: 3.13
Classifier: Programming Language :: Python :: 3.14
Classifier: Topic :: Software Development
Requires-Dist: Django (>=5.2,<6.0)
Requires-Dist: Jinja2 (>=3.1.1,<4.0.0)
Requires-Dist: PyJWT (>=2.4.0,<3.0.0)
Requires-Dist: click (>=8.2.0,<9.0.0)
Requires-Dist: django-cors-headers (>=4.6.0,<5.0.0)
Requires-Dist: django-graphql-jwt (>=0.4.0,<0.5.0)
Requires-Dist: django-rq (>=3.1,<4.0)
Requires-Dist: django-storages[google] (>=1.13.2,<2.0.0)
Requires-Dist: django-treebeard (>=4.5.1,<5.0.0)
Requires-Dist: google-auth (>=2.18.0,<3.0.0)
Requires-Dist: graphene-django (>=3.2.3,<4.0.0)
Requires-Dist: grimoirelab-toolkit (>=0.3)
Requires-Dist: mysqlclient (>=2.2.7,<3.0.0)
Requires-Dist: pandas (>=2.2,<3.0)
Requires-Dist: python-dateutil (>=2.8.2,<3.0.0)
Requires-Dist: requests (>=2.7.0,<3.0.0)
Requires-Dist: rq (>=2.5.0,<3.0.0)
Requires-Dist: sgqlc (>=16.1,<17.0)
Requires-Dist: uWSGI (>=2.0,<3.0)
Project-URL: Bug Tracker, https://github.com/chaoss/grimoirelab-sortinghat/issues
Project-URL: Homepage, https://chaoss.github.io/grimoirelab/
Project-URL: Repository, https://github.com/chaoss/grimoirelab-sortinghat
